namegender
