Metadata-Version: 1.2
Name: namegender
Version: 1.0.2
Summary: Predict the gender of a name based on statistic data
Home-page: https://github.com/samuorous/namegender
Author: Samuorous
Author-email: samuorous@gmail.com
License: GPLv3
Project-URL: Source, https://github.com/samuorous/namegender
Project-URL: Bug Reports, https://github.com/samuorous/namegender/issues
Keywords: name gender prediction
Platform: UNKNOWN
